{"openapi":"3.1.0","info":{"title":"FastAPI","version":"0.1.0"},"paths":{"/analyze-text":{"post":{"summary":"Analyze Text","operationId":"analyze_text_analyze_text_post","requestBody":{"content":{"application/json":{"schema":{"$ref":"#/components/schemas/TextInput"}}},"required":true},"responses":{"200":{"description":"Successful Response","content":{"application/json":{"schema":{"$ref":"#/components/schemas/TextOutput"}}}},"422":{"description":"Validation Error","content":{"application/json":{"schema":{"$ref":"#/components/schemas/HTTPValidationError"}}}}}}}},"components":{"schemas":{"HTTPValidationError":{"properties":{"detail":{"items":{"$ref":"#/components/schemas/ValidationError"},"type":"array","title":"Detail"}},"type":"object","title":"HTTPValidationError"},"TextInput":{"properties":{"message":{"type":"string","title":"Message","description":"Texto da mensagem a ser analisada"}},"type":"object","required":["message"],"title":"TextInput"},"TextOutput":{"properties":{"risk":{"type":"string","title":"Risk","description":"Classificação da IA (ex: 'golpe', 'legítima')"},"confidence":{"type":"number","maximum":1.0,"minimum":0.0,"title":"Confidence","description":"Nível de confiança (0 a 1)"},"reason":{"type":"string","title":"Reason","description":"Motivo gerado pela IA para a classificação"}},"type":"object","required":["risk","confidence","reason"],"title":"TextOutput"},"ValidationError":{"properties":{"loc":{"items":{"anyOf":[{"type":"string"},{"type":"integer"}]},"type":"array","title":"Location"},"msg":{"type":"string","title":"Message"},"type":{"type":"string","title":"Error Type"}},"type":"object","required":["loc","msg","type"],"title":"ValidationError"}}}}